[
    {
        "timestamp":  "2025-09-25T08:58:18.9687134+01:00",
        "details":  {
                        "name":  "SBS-BN-SHOES-UK-9-5-20250925-644.jpeg"
                    },
        "action":  "CREATE",
        "itemId":  "b0911584"
    },
    {
        "timestamp":  "2025-09-25T09:00:56.8172120+01:00",
        "details":  {
                        "name":  "SBS-BN-SHOES-UK-9-5-20250925-115.jpeg"
                    },
        "action":  "CREATE",
        "itemId":  "36d0d4da"
    },
    {
        "timestamp":  "2025-09-25T09:01:25.0915878+01:00",
        "details":  {
                        "name":  "SBS-BN-SHOES-UK-9-5-20250925-945.jpeg"
                    },
        "action":  "CREATE",
        "itemId":  "962c6a75"
    },
    {
        "timestamp":  "2025-09-25T09:13:42.2033257+01:00",
        "details":  {
                        "fields":  "tags",
                        "tags":  "LIVE, FEATURED, DELETED"
                    },
        "action":  "UPDATE",
        "itemId":  "b0911584"
    },
    {
        "timestamp":  "2025-09-25T09:18:17.7289471+01:00",
        "details":  {
                        "name":  "SBS-BN-SHOES-UK-9-20250925-363.jpeg"
                    },
        "action":  "CREATE",
        "itemId":  "a8b81a8a"
    },
    {
        "timestamp":  "2025-09-25T09:22:42.3423438+01:00",
        "details":  {
                        "name":  "SBS-BN-CLOTHES-XS-20250925-075.jpeg"
                    },
        "action":  "CREATE",
        "itemId":  "8bced243"
    },
    {
        "timestamp":  "2025-09-25T09:38:07.0565913+01:00",
        "details":  {
                        "name":  "BN-CLOTHES-XS-20250925-0938-B09250938-001.jpeg"
                    },
        "action":  "CREATE",
        "itemId":  "4b922230"
    },
    {
        "timestamp":  "2025-09-25T09:43:59.8190892+01:00",
        "details":  {
                        "name":  "CAT-BN-SHOES-SIZE-UK12-DATE-20250925-TIME-0943-BATCH-B09250943-ITEM-001.jpeg"
                    },
        "action":  "CREATE",
        "itemId":  "df95a3e6"
    },
    {
        "timestamp":  "2025-09-25T09:50:00.1991542+01:00",
        "details":  {
                        "fields":  "tags",
                        "tags":  "LIVE, STAFF-PICKS, BESTSELLER, DELETED"
                    },
        "action":  "UPDATE",
        "itemId":  "a8b81a8a"
    },
    {
        "timestamp":  "2025-09-25T09:51:20.5372188+01:00",
        "details":  {
                        "name":  "CAT-BN-SHOES-SIZE-UK105-DATE-20250925-TIME-0951-BATCH-B09250951-ITEM-001.jpeg"
                    },
        "action":  "CREATE",
        "itemId":  "8bb480d1"
    },
    {
        "timestamp":  "2025-09-25T09:51:24.2567977+01:00",
        "details":  {
                        "fields":  "cloudflareId, filename, name, category, size, tags, status, notes, id, createdAt, updatedAt, image, imageStatus, needsUpdate, deleteReason",
                        "tags":  "LIVE, FEATURED, DELETED"
                    },
        "action":  "UPDATE",
        "itemId":  "8bb480d1"
    }
]
